CHANGES.txt
CONTRIBUTORS.txt
MANIFEST.in
README.txt
setup.cfg
setup.py
docs/LICENSE.LGPL
docs/LICENSE.txt
src/fnord/__init__.py
src/fnord.safename.egg-info/PKG-INFO
src/fnord.safename.egg-info/SOURCES.txt
src/fnord.safename.egg-info/dependency_links.txt
src/fnord.safename.egg-info/entry_points.txt
src/fnord.safename.egg-info/namespace_packages.txt
src/fnord.safename.egg-info/not-zip-safe
src/fnord.safename.egg-info/requires.txt
src/fnord.safename.egg-info/top_level.txt
src/fnord/safename/__init__.py
src/fnord/safename/codec.py
src/fnord/safename/script.py
src/fnord/safename/tests.py