Metadata-Version: 1.0
Name: fnord.safename
Version: 0.5
Summary: A codec for safe filenames.
Home-page: https://github.com/batlock666/fnord.safename
Author: Bert Vanderbauwhede
Author-email: batlock666@gmail.com
License: lgpl
Keywords: codec safename
Platform: UNKNOWN
Classifier: Development Status :: 5 - Production/Stable
Classifier: Environment :: Console
Classifier: License :: OSI Approved :: GNU Library or Lesser General Public License (LGPL)
Classifier: Operating System :: OS Independent
Classifier: Programming Language :: Python
Classifier: Topic :: Software Development :: Libraries :: Python Modules
Classifier: Topic :: Utilities
